jsonical3.py
jsonical3-0.1.0.dist-info/LICENSE
jsonical3-0.1.0.dist-info/METADATA
jsonical3-0.1.0.dist-info/WHEEL
jsonical3-0.1.0.dist-info/top_level.txt
jsonical3-0.1.0.dist-info/zip-safe
jsonical3-0.1.0.dist-info/RECORD
